drf_channels/__init__.py
drf_channels/apps.py
drf_channels/mixins.py
drf_channels/utils.py
drf_channels/bindings/__init__.py
drf_channels/bindings/base.py
drf_channels/bindings/resource.py
drf_channels-0.1.1.dist-info/METADATA
drf_channels-0.1.1.dist-info/RECORD
drf_channels-0.1.1.dist-info/WHEEL
drf_channels-0.1.1.dist-info/top_level.txt
tests/__init__.py
tests/bindings.py
tests/consumers.py
tests/models.py
tests/routing.py
tests/test_mixins.py
tests/test_settings.py
