Metadata-Version: 2.1
Name: drf-channels
Version: 0.1.1
Summary: Simple Resource binding and Consumer Mixin for Django Rest Framework and Channels 2
Home-page: https://github.com/iamriel/drf-channels
Author: Rieljun Liguid
Author-email: me@iamriel.com
License: MIT
Platform: UNKNOWN
Classifier: Environment :: Web Environment
Classifier: Programming Language :: Python
Classifier: Programming Language :: Python :: 3.5
Classifier: Programming Language :: Python :: 3.6
Requires-Dist: Django (>=1.11)
Requires-Dist: channels (>=2.0)
Requires-Dist: djangorestframework (>=3.0)
